buildNanoGPT/__init__.py
buildNanoGPT/_modidx.py
buildNanoGPT/data.py
buildNanoGPT/model.py
buildNanoGPT/train.py
buildNanoGPT/viz.py
buildNanoGPT-0.1.6.dist-info/LICENSE
buildNanoGPT-0.1.6.dist-info/METADATA
buildNanoGPT-0.1.6.dist-info/WHEEL
buildNanoGPT-0.1.6.dist-info/entry_points.txt
buildNanoGPT-0.1.6.dist-info/top_level.txt
buildNanoGPT-0.1.6.dist-info/RECORD
