Metadata-Version: 2.1
Name: buildNanoGPT
Version: 0.1.6
Summary: A template for nbdev-based project
Home-page: https://github.com/hdocmsu/buildNanoGPT/
Author: Hung Do, PhD
Author-email: clinicalcollaborations@gmail.com
License: Apache Software License 2.0
Keywords: nbdev
Classifier: Development Status :: 3 - Alpha
Classifier: Intended Audience :: Developers
Classifier: Natural Language :: English
Classifier: Programming Language :: Python :: 3.7
Classifier: Programming Language :: Python :: 3.8
Classifier: Programming Language :: Python :: 3.9
Classifier: Programming Language :: Python :: 3.10
Classifier: License :: OSI Approved :: Apache Software License
Requires-Python: >=3.7
License-File: LICENSE
Requires-Dist: numpy
Requires-Dist: matplotlib
Provides-Extra: dev
